jupyter_extension_sigmund.py
jupyter_extension_sigmund-0.2.0.dist-info/licenses/COPYING
jupyter_extension_sigmund-0.2.0.dist-info/WHEEL
jupyter_extension_sigmund-0.2.0.dist-info/METADATA
jupyter_extension_sigmund-0.2.0.dist-info/RECORD
