Metadata-Version: 2.4
Name: jupyter-extension-sigmund
Version: 0.2.0
Summary: This is an extension for Jupyterlab, Jupyter Notebook, Spyder, Rapunzel, or any other application that uses a Jupyter/ IPython based console. It allows you to connect your Python session to [SigmundAI](https://sigmundai.eu). This is mainly intended as a tool for coding and data analysis.
Keywords: data analysis,artifical intelligence,jupyter,ipython
Author-email: Sebastiaan Mathôt <s.mathot@cogsci.nl>
Requires-Python: >=3.8
License-File: COPYING
Requires-Dist: websockets
Project-URL: Documentation, https://sigmundai.eu
Project-URL: Source, https://github.com/open-cogsci/jupyter-extension-sigmund
